sumomongodbatlascollector/__init__.py
sumomongodbatlascollector/api.py
sumomongodbatlascollector/main.py
sumomongodbatlascollector/mongodbatlas.yaml
sumomongodbatlascollector/time_and_memory_tracker.py
sumologic_mongodb_atlas-1.0.11.dist-info/LICENSE
sumologic_mongodb_atlas-1.0.11.dist-info/METADATA
sumologic_mongodb_atlas-1.0.11.dist-info/WHEEL
sumologic_mongodb_atlas-1.0.11.dist-info/entry_points.txt
sumologic_mongodb_atlas-1.0.11.dist-info/top_level.txt
sumologic_mongodb_atlas-1.0.11.dist-info/zip-safe
sumologic_mongodb_atlas-1.0.11.dist-info/RECORD
