Metadata-Version: 2.1
Name: sumologic-mongodb-atlas
Version: 1.0.11
Summary: Sumo Logic collection solution for mongodb atlas
Home-page: https://github.com/SumoLogic/sumologic-mongodb-atlas
Author: SumoLogic
Author-email: it@sumologic.com
License: PSF
Keywords: sumologic python rest api log management analytics logreduce mongodb atlas agent security siem collector forwarder
Classifier: Development Status :: 4 - Beta
Classifier: Intended Audience :: Developers
Classifier: Programming Language :: Python :: 2.7
Classifier: Programming Language :: Python :: 3.7
Classifier: Programming Language :: Python :: 3.8
Classifier: Programming Language :: Python :: 3.9
Classifier: Programming Language :: Python :: 3.10
Classifier: Programming Language :: Python :: 3.11
Classifier: Programming Language :: Python :: 3.12
Classifier: Operating System :: OS Independent
License-File: LICENSE
Requires-Dist: sumologic-appclient-sdk>=2.0.10
Requires-Dist: requests>=2.32.3
Requires-Dist: future-fstrings==1.2.0
Provides-Extra: aws
Requires-Dist: boto3>=1.34.149; extra == "aws"
Requires-Dist: botocore>=1.34.149; extra == "aws"
Provides-Extra: azure
Requires-Dist: azure-cosmosdb-table>=1.0.6; extra == "azure"
Requires-Dist: bson>=0.5.10; extra == "azure"
Provides-Extra: gcp
Requires-Dist: google-api-python-client>=2.129.0; extra == "gcp"
Requires-Dist: oauth2client>=4.1.3; extra == "gcp"
Requires-Dist: google-cloud-datastore>=2.19.0; extra == "gcp"
